poetry_rak/__init__.py
poetry_rak-0.1.0.dist-info/entry_points.txt
poetry_rak-0.1.0.dist-info/WHEEL
poetry_rak-0.1.0.dist-info/METADATA
poetry_rak-0.1.0.dist-info/RECORD
